cdl_parser/__init__.py
cdl_parser/cli.py
cdl_parser/constants.py
cdl_parser/exceptions.py
cdl_parser/models.py
cdl_parser/parser.py
cdl_parser/py.typed
gemmology_cdl_parser-1.0.1.dist-info/licenses/LICENSE
gemmology_cdl_parser-1.0.1.dist-info/METADATA
gemmology_cdl_parser-1.0.1.dist-info/WHEEL
gemmology_cdl_parser-1.0.1.dist-info/entry_points.txt
gemmology_cdl_parser-1.0.1.dist-info/top_level.txt
gemmology_cdl_parser-1.0.1.dist-info/RECORD
