Metadata-Version: 2.4
Name: gemmology-cdl-parser
Version: 1.0.1
Summary: Crystal Description Language (CDL) parser for crystallographic visualization
Author-email: Fabian Schuh <fabian@gemmology.dev>
Maintainer-email: Fabian Schuh <fabian@gemmology.dev>
License: MIT
Project-URL: Homepage, https://cdl-parser.gemmology.dev
Project-URL: Documentation, https://cdl-parser.gemmology.dev/docs
Project-URL: Repository, https://github.com/gemmology-dev/cdl-parser
Project-URL: Issues, https://github.com/gemmology-dev/cdl-parser/issues
Project-URL: Changelog, https://github.com/gemmology-dev/cdl-parser/blob/main/CHANGELOG.md
Keywords: crystallography,mineralogy,gemmology,parser,crystal,miller-index,crystal-morphology,visualization
Classifier: Development Status :: 5 - Production/Stable
Classifier: Intended Audience :: Science/Research
Classifier: Intended Audience :: Education
Classifier: License :: OSI Approved :: MIT License
Classifier: Operating System :: OS Independent
Classifier: Programming Language :: Python :: 3
Classifier: Programming Language :: Python :: 3.10
Classifier: Programming Language :: Python :: 3.11
Classifier: Programming Language :: Python :: 3.12
Classifier: Programming Language :: Python :: 3.13
Classifier: Topic :: Scientific/Engineering
Classifier: Topic :: Scientific/Engineering :: Chemistry
Classifier: Topic :: Scientific/Engineering :: Visualization
Classifier: Typing :: Typed
Requires-Python: >=3.10
License-File: LICENSE
Provides-Extra: dev
Requires-Dist: pytest>=7.0; extra == "dev"
Requires-Dist: pytest-cov>=4.0; extra == "dev"
Requires-Dist: ruff>=0.1.0; extra == "dev"
Requires-Dist: mypy>=1.0; extra == "dev"
Provides-Extra: docs
Requires-Dist: mkdocs>=1.5; extra == "docs"
Requires-Dist: mkdocs-material>=9.0; extra == "docs"
Requires-Dist: mkdocstrings[python]>=0.24; extra == "docs"
Dynamic: license-file
